Metadata-Version: 2.1
Name: aerialist
Version: 0.2.1
Summary: UAV Test Bench
Home-page: https://github.com/skhatiri/Aerialist
Author: Sajad Khatiri
Author-email: s.khatiri@gmail.com
License: MIT
Project-URL: Bug Tracker, https://github.com/skhatiri/Aerialist/issues
Requires-Python: >=3.7
License-File: LICENSE.md
Requires-Dist: numpy ==1.23.2
Requires-Dist: similaritymeasures ==0.5.0
Requires-Dist: matplotlib >=3.6.0
Requires-Dist: pyulog ==0.9.0
Requires-Dist: mavsdk ==1.4.1
Requires-Dist: keyboard ==0.13.5
Requires-Dist: python-decouple ==3.6
Requires-Dist: csv-logger ==1.3.0
Requires-Dist: statsmodels ==0.13.2
Requires-Dist: webdavclient3 ==3.14.6
Requires-Dist: ruptures ==1.1.7
Requires-Dist: shapely ==1.8.4
Requires-Dist: validators ==0.20.0
Requires-Dist: pyyaml ==6.0
Requires-Dist: munch ==2.5.0
Requires-Dist: rospkg ==1.4.0
Requires-Dist: defusedxml ==0.7.1
Requires-Dist: tslearn ==0.5.2
Requires-Dist: h5py ==3.9.0
